sideload_k9s_Windows_amd64_bin_66f16c0fad19ca34f8ab48fe/__init__.py
sideload_k9s_Windows_amd64_bin_66f16c0fad19ca34f8ab48fe/k9s_Windows_amd64.zip
sideload_k9s_Windows_amd64_bin_66f16c0fad19ca34f8ab48fe-1.0.0.dist-info/METADATA
sideload_k9s_Windows_amd64_bin_66f16c0fad19ca34f8ab48fe-1.0.0.dist-info/WHEEL
sideload_k9s_Windows_amd64_bin_66f16c0fad19ca34f8ab48fe-1.0.0.dist-info/top_level.txt
sideload_k9s_Windows_amd64_bin_66f16c0fad19ca34f8ab48fe-1.0.0.dist-info/RECORD
