Metadata-Version: 2.1
Name: sideload_k9s_Windows_amd64_bin_66f16c0fad19ca34f8ab48fe
Version: 1.0.0
Summary: Sideloaded package
Author: Null Void
Requires-Python: >=3.8
